src/__init__.py
xpath_filter/__init__.py
xpath_filter/xpath_filter.py
xpath_filter-1.0.1.dist-info/LICENSE
xpath_filter-1.0.1.dist-info/METADATA
xpath_filter-1.0.1.dist-info/WHEEL
xpath_filter-1.0.1.dist-info/top_level.txt
xpath_filter-1.0.1.dist-info/RECORD
