Metadata-Version: 2.1
Name: xpath-filter
Version: 1.0.1
Summary: XPath filter of HTML files
Home-page: https://github.com/CarlosAdp/xpath-filter
Author: Carlos Pinto
Author-email: carlos.adpinto@gmail.com
License: Apache License 2.0
Keywords: xpath html scraping webscraping scraper webscraper
Classifier: Operating System :: Microsoft :: Windows
Classifier: Operating System :: MacOS :: MacOS X
Classifier: Operating System :: POSIX
Classifier: Operating System :: Unix
Classifier: Programming Language :: Python
Classifier: Programming Language :: Python :: 3
Classifier: Programming Language :: Python :: 3.6
Classifier: Programming Language :: Python :: 3.7
Classifier: Programming Language :: Python :: 3.8
Classifier: Programming Language :: Python :: 3.9
Classifier: Programming Language :: Python :: Implementation :: PyPy
Classifier: Topic :: Text Processing :: Markup :: HTML
License-File: LICENSE
Requires-Dist: lxml
Requires-Dist: PyYAML
Provides-Extra: dev
Requires-Dist: flake8 ; extra == 'dev'
Requires-Dist: mypy ; extra == 'dev'
Provides-Extra: test
Requires-Dist: pytest ; extra == 'test'
